MANIFEST.in
README.md
setup.py
src/py2_em/__init__.py
src/py2_em/py2emulator.py
src/py2_em.egg-info/PKG-INFO
src/py2_em.egg-info/SOURCES.txt
src/py2_em.egg-info/dependency_links.txt
src/py2_em.egg-info/requires.txt
src/py2_em.egg-info/top_level.txt
src/py2em_ext/include/logging.h
src/py2em_ext/include/marshal_datatypes.h
src/py2em_ext/include/marshal_utils.h
src/py2em_ext/include/py2_decref.h
src/py2em_ext/include/py2em_extension.h
src/py2em_ext/source/logging.c
src/py2em_ext/source/marshal_datatypes.c
src/py2em_ext/source/marshal_utils.c
src/py2em_ext/source/py2em_extension.c
test/test_py2_em.py