Metadata-Version: 2.1
Name: py2-em
Version: 1.0.0
Summary: Execute Python code in an emulated Python2 terminal (within Python3)
Home-page: https://github.com/chrisBrookes93/Py2Em
Author: Chris Brookes
Author-email: chris_b_856@hotmail.com
License: MIT
Platform: UNKNOWN
Classifier: Development Status :: 4 - Beta
Classifier: Programming Language :: Python :: 3
Classifier: License :: OSI Approved :: MIT License
Classifier: Operating System :: POSIX :: Linux
Classifier: Operating System :: Microsoft :: Windows
Requires-Python: >=3
Provides-Extra: dev
